pydantic_settings_sops/__init__.py
pydantic_settings_sops-0.1.2.dist-info/licenses/LICENSE
pydantic_settings_sops-0.1.2.dist-info/METADATA
pydantic_settings_sops-0.1.2.dist-info/WHEEL
pydantic_settings_sops-0.1.2.dist-info/top_level.txt
pydantic_settings_sops-0.1.2.dist-info/RECORD
