Metadata-Version: 2.4
Name: pydantic-settings-sops
Version: 0.1.2
Summary: SOPS extension for pydantic-settings
Author-email: Pavel Zwerschke <pavelzw@gmail.com>
Project-URL: repository, https://github.com/pavelzw/pydantic-settings-sops
Classifier: Programming Language :: Python :: 3
Classifier: Programming Language :: Python :: 3.10
Classifier: Programming Language :: Python :: 3.11
Classifier: Programming Language :: Python :: 3.12
Requires-Python: >=3.10
License-File: LICENSE
Requires-Dist: pydantic-settings<3,>=2.9.1
Requires-Dist: sopsy<2,>=1.0.1
Dynamic: license-file
